DobotTCP/DobotTCP.py
DobotTCP/__init__.py
dobottcp-1.1.6.dist-info/METADATA
dobottcp-1.1.6.dist-info/WHEEL
dobottcp-1.1.6.dist-info/licenses/LICENSE
dobottcp-1.1.6.dist-info/RECORD
