Metadata-Version: 2.4
Name: DobotTCP
Version: 1.1.6
Summary: A library to control Dobot robots via TCP
Project-URL: Homepage, https://github.com/MichaelHengge/DobotTCP
Project-URL: Issues, https://github.com/MichaelHengge/DobotTCP/issues
Author-email: Michael Hengge <michael.hengge@physik.hu-berlin.de>
License-Expression: MIT
License-File: LICENSE
Keywords: dobot,robotics,tcp
Classifier: Operating System :: OS Independent
Classifier: Programming Language :: Python :: 3
Requires-Python: >=3.8
Requires-Dist: multipledispatch>=1.0.0
